cascade_filtering/__init__.py
cascade_filtering/filtering.py
cascade_filtering/initialize.py
cascade_filtering/kernel.py
cascade_filtering/stencil.py
cascade_filtering/utilities.py
cascade_filtering-1.0.4.data/data/LICENSE.txt
cascade_filtering-1.0.4.data/data/README.md
cascade_filtering-1.0.4.data/scripts/setup_cascade-filtering.py
cascade_filtering-1.0.4.dist-info/licenses/LICENSE.txt
configuration_files/anisotropic_gaussian_kernel.conf
configuration_files/anisotropic_gaussian_kernel_2d.conf
configuration_files/banana_kernel.conf
configuration_files/edge_filter.conf
configuration_files/kuwahara_kernel.conf
configuration_files/nagano_matsuyama_kernel.conf
cascade_filtering-1.0.4.dist-info/METADATA
cascade_filtering-1.0.4.dist-info/WHEEL
cascade_filtering-1.0.4.dist-info/top_level.txt
cascade_filtering-1.0.4.dist-info/RECORD
