Metadata-Version: 2.4
Name: CASCADe-filtering
Version: 1.0.4
Summary: CASCADe filtering: Calibration of trAnsit Spectroscopy using CAusal Data filtering module.
Home-page: https://jbouwman.gitlab.io/CASCADe-filtering/
Download-URL: https://gitlab.com/jbouwman/CASCADe-filtering
Author: Jeroen Bouwman
Author-email: bouwman@mpia.de
License: GNU General Public License v3 (GPLv3)
Classifier: Programming Language :: Python :: 3
Classifier: License :: OSI Approved :: GNU General Public License v3 (GPLv3)
Classifier: Operating System :: OS Independent
Classifier: Intended Audience :: Science/Research
Classifier: Topic :: Scientific/Engineering :: Astronomy
Requires-Python: >=3.9, <3.13
License-File: LICENSE.txt
Requires-Dist: astropy
Requires-Dist: scipy
Requires-Dist: numpy
Requires-Dist: configparser
Requires-Dist: jupyter
Requires-Dist: matplotlib
Requires-Dist: tqdm
Requires-Dist: seaborn
Requires-Dist: pytest
Requires-Dist: scikit-image>=0.19
Requires-Dist: sphinx
Requires-Dist: alabaster
Requires-Dist: pyfiglet
Requires-Dist: six
Requires-Dist: colorama
Requires-Dist: termcolor
Requires-Dist: cython
Requires-Dist: numba
Requires-Dist: ray[default]
Dynamic: author
Dynamic: author-email
Dynamic: classifier
Dynamic: description
Dynamic: description-content-type
Dynamic: download-url
Dynamic: home-page
Dynamic: license
Dynamic: license-file
Dynamic: requires-dist
Dynamic: requires-python
Dynamic: summary
